[
  {
    "train_loss": 5.464873338422032,
    "val_loss": 0.23735583875375457,
    "val_acc": 0.5824,
    "forget_acc": 0.001,
    "retain_acc": 0.647,
    "epoch": 0
  },
  {
    "train_loss": 5.107390863675597,
    "val_loss": 0.2418572208549403,
    "val_acc": 0.5913,
    "forget_acc": 0.0,
    "retain_acc": 0.657,
    "epoch": 1
  },
  {
    "train_loss": 4.935249490940825,
    "val_loss": 0.24210309161792828,
    "val_acc": 0.5964,
    "forget_acc": 0.0,
    "retain_acc": 0.6626666666666666,
    "epoch": 2
  },
  {
    "train_loss": 4.835907743332234,
    "val_loss": 0.240252114643779,
    "val_acc": 0.6052,
    "forget_acc": 0.0,
    "retain_acc": 0.6724444444444444,
    "epoch": 3
  },
  {
    "train_loss": 4.76942929139374,
    "val_loss": 0.234930841558719,
    "val_acc": 0.6086,
    "forget_acc": 0.0,
    "retain_acc": 0.6762222222222222,
    "epoch": 4
  },
  {
    "train_loss": 4.687130665948205,
    "val_loss": 0.22496849279614944,
    "val_acc": 0.6108,
    "forget_acc": 0.0,
    "retain_acc": 0.6786666666666666,
    "epoch": 5
  },
  {
    "train_loss": 4.629391036135085,
    "val_loss": 0.2299518008963971,
    "val_acc": 0.6124,
    "forget_acc": 0.0,
    "retain_acc": 0.6804444444444444,
    "epoch": 6
  },
  {
    "train_loss": 4.575323470940827,
    "val_loss": 0.22929436798337138,
    "val_acc": 0.619,
    "forget_acc": 0.0,
    "retain_acc": 0.6877777777777778,
    "epoch": 7
  },
  {
    "train_loss": 4.481992675902996,
    "val_loss": 0.24105437760111653,
    "val_acc": 0.6227,
    "forget_acc": 0.0,
    "retain_acc": 0.6918888888888889,
    "epoch": 8
  },
  {
    "train_loss": 4.4550906986209515,
    "val_loss": 0.23805702619160277,
    "val_acc": 0.6263,
    "forget_acc": 0.0,
    "retain_acc": 0.6958888888888889,
    "epoch": 9
  },
  {
    "train_loss": 4.406233329299494,
    "val_loss": 0.2251255631069594,
    "val_acc": 0.6313,
    "forget_acc": 0.0,
    "retain_acc": 0.7014444444444444,
    "epoch": 10
  },
  {
    "train_loss": 4.335228597018736,
    "val_loss": 0.21812857036726385,
    "val_acc": 0.6299,
    "forget_acc": 0.0,
    "retain_acc": 0.6998888888888889,
    "epoch": 11
  }
]